setup.py
kpss_py3/__init__.py
kpss_py3/kpss_py3.py
kpss_py3.egg-info/PKG-INFO
kpss_py3.egg-info/SOURCES.txt
kpss_py3.egg-info/dependency_links.txt
kpss_py3.egg-info/not-zip-safe
kpss_py3.egg-info/top_level.txt