Metadata-Version: 1.0
Name: kpss-py3
Version: 0.1
Summary: Python 3 implementation of the Kraaij-Pohlmann Snowball Stemmer
Home-page: http://github.com/thomasbrockmeier/kpss_py3
Author: Thomas Brockmeier
Author-email: thomas.brockmeier@gmail.com
License: MIT
Platform: UNKNOWN
